{"_invocation_id": "abc439ba-c1ba-42bb-b196-3d3e73f6ed5f", "linked": {"0": {"name": "source.mnemos.mnemos.assets", "type": "source", "succ": [5]}, "1": {"name": "source.mnemos.mnemos.users", "type": "source", "succ": [5]}, "2": {"name": "source.mnemos.mnemos.consents", "type": "source", "succ": [6]}, "3": {"name": "source.mnemos.mnemos.asset_views", "type": "source"}, "4": {"name": "source.mnemos.mnemos.categories", "type": "source"}, "5": {"name": "model.mnemos.assets_summary", "type": "model"}, "6": {"name": "model.mnemos.consents_summary", "type": "model"}}}